aio_geojson_nsw_transport_incidents/__init__.py
aio_geojson_nsw_transport_incidents/__version__.py
aio_geojson_nsw_transport_incidents/consts.py
aio_geojson_nsw_transport_incidents/feed.py
aio_geojson_nsw_transport_incidents/feed_entry.py
aio_geojson_nsw_transport_incidents/feed_manager.py
aio_geojson_nsw_transport_incidents-0.1.dist-info/LICENSE
aio_geojson_nsw_transport_incidents-0.1.dist-info/METADATA
aio_geojson_nsw_transport_incidents-0.1.dist-info/WHEEL
aio_geojson_nsw_transport_incidents-0.1.dist-info/top_level.txt
aio_geojson_nsw_transport_incidents-0.1.dist-info/RECORD
