Metadata-Version: 2.1
Name: aio-geojson-nsw-transport-incidents
Version: 0.1
Summary: An async GeoJSON client library for NSW Transport Service Incidents.
Home-page: https://github.com/Fred-Ch/python-aio-geojson-nsw-transport-incidents-master
Author: Fred Chauland
Author-email: frederic.chauland@gmail.com
License: UNKNOWN
Platform: UNKNOWN
Classifier: Programming Language :: Python :: 3.6
Classifier: Programming Language :: Python :: 3.7
Classifier: Programming Language :: Python :: 3.8
Classifier: License :: OSI Approved :: Apache Software License
Classifier: Operating System :: OS Independent
Requires-Dist: aio-geojson-client (>=0.13)
Requires-Dist: aiohttp (>=3.5.4)
Requires-Dist: pytz (>=2019.01)
